LICENSE
MANIFEST.in
README
setup.py
django_tellafriend.egg-info/PKG-INFO
django_tellafriend.egg-info/SOURCES.txt
django_tellafriend.egg-info/dependency_links.txt
django_tellafriend.egg-info/top_level.txt
docs/source/conf.py
docs/source/configuration.rst
docs/source/index.rst
docs/source/installation.rst
docs/source/license.rst
docs/source/prerequisites.rst
docs/source/templates.rst
tellafriend/__init__.py
tellafriend/forms.py
tellafriend/models.py
tellafriend/urls.py
tellafriend/views.py
tellafriend/locale/de/LC_MESSAGES/django.mo
tellafriend/locale/de/LC_MESSAGES/django.po
tellafriend/templates/tellafriend/email.html
tellafriend/templates/tellafriend/email.txt
tellafriend/templates/tellafriend/success.html
tellafriend/templates/tellafriend/tellafriend.html