Metadata-Version: 1.0
Name: django-tellafriend
Version: 0.0.10
Summary: Tell-a-friend functionality for Django-based websites
Home-page: http://github.com/philippbosch/django-tellafriend/
Author: Philipp Bosch
Author-email: hello@pb.io
License: MIT
Keywords: django tellafriend recommend
Platform: UNKNOWN
Classifier: Development Status :: 3 - Alpha
Classifier: Environment :: Web Environment
Classifier: Operating System :: OS Independent
Classifier: Programming Language :: Python
Classifier: Framework :: Django
Classifier: License :: OSI Approved :: MIT License
